dbaicd10/__init__.py
dbaicd10/search.py
dbaicd10/__pycache__/__init__.cpython-36.pyc
dbaicd10/__pycache__/search.cpython-36.pyc
dbaicd10/resources/__init__.py
dbaicd10/resources/dba_icd10.csv
dbaicd10/resources/vocab_list.pkl
dbaicd10/resources/__pycache__/__init__.cpython-36.pyc
dbaicdten-0.0.4.dist-info/METADATA
dbaicdten-0.0.4.dist-info/RECORD
dbaicdten-0.0.4.dist-info/WHEEL
dbaicdten-0.0.4.dist-info/top_level.txt
