Metadata-Version: 2.1
Name: dbaicdten
Version: 0.0.4
Summary: High level api for dbaicd10 code
Home-page: https://github.com/blaze4o4/dbaicdten
Author: Devyani Kulkarni
Author-email: devyanikul12345@gmail.com
License: UNKNOWN
Download-URL: https://github.com/blaze4o4/dbaicdten/archive/0.0.4.tar.gz
Platform: UNKNOWN
Classifier: Programming Language :: Python :: 3
Classifier: License :: OSI Approved :: MIT License
Classifier: Operating System :: OS Independent
Requires-Python: >=3.6
